scrapy_redis/__init__.py
scrapy_redis/bucket_hash.py
scrapy_redis/connection.py
scrapy_redis/defaults.py
scrapy_redis/dupefilter.py
scrapy_redis/picklecompat.py
scrapy_redis/pipelines.py
scrapy_redis/queue.py
scrapy_redis/scheduler.py
scrapy_redis/spiders.py
scrapy_redis/stats.py
scrapy_redis/utils.py
deepctrl_scrapy_redis-0.8.5.dist-info/AUTHORS.rst
deepctrl_scrapy_redis-0.8.5.dist-info/LICENSE
deepctrl_scrapy_redis-0.8.5.dist-info/METADATA
deepctrl_scrapy_redis-0.8.5.dist-info/WHEEL
deepctrl_scrapy_redis-0.8.5.dist-info/top_level.txt
deepctrl_scrapy_redis-0.8.5.dist-info/RECORD
