Metadata-Version: 2.1
Name: deepctrl-scrapy-redis
Version: 0.8.5
Summary: Redis-based components for Scrapy.
Home-page: https://github.com/alexKeleon/scrapy-redis
Author: yihcao.wu
Author-email: rolando@rmax.io
License: MIT
Keywords: deepctrl-scrapy-redis
Platform: UNKNOWN
Classifier: Development Status :: 4 - Beta
Classifier: Intended Audience :: Developers
Classifier: License :: OSI Approved :: MIT License
Classifier: Natural Language :: English
Classifier: Programming Language :: Python :: 2
Classifier: Programming Language :: Python :: 2.7
Classifier: Programming Language :: Python :: 3
Classifier: Programming Language :: Python :: 3.4
Classifier: Programming Language :: Python :: 3.5
Requires-Dist: Scrapy (>=1.0)
Requires-Dist: redis (>=2.10)
Requires-Dist: six (>=1.5.2)
Requires-Dist: mmh3 (>=3.0.0)
